centimators/__init__.py
centimators/config.py
centimators/losses.py
centimators/narwhals_utils.py
centimators/py.typed
centimators/feature_transformers/__init__.py
centimators/feature_transformers/base.py
centimators/feature_transformers/dimreduction.py
centimators/feature_transformers/embedding.py
centimators/feature_transformers/neutralization.py
centimators/feature_transformers/penalization.py
centimators/feature_transformers/ranking.py
centimators/feature_transformers/stats.py
centimators/feature_transformers/time_series.py
centimators/model_estimators/__init__.py
centimators/model_estimators/dspymator.py
centimators/model_estimators/keras_cortex.py
centimators/model_estimators/keras_estimators/__init__.py
centimators/model_estimators/keras_estimators/autoencoder.py
centimators/model_estimators/keras_estimators/base.py
centimators/model_estimators/keras_estimators/dense.py
centimators/model_estimators/keras_estimators/sequence.py
centimators/model_estimators/keras_estimators/tree.py
centimators-0.3.2.dist-info/METADATA
centimators-0.3.2.dist-info/WHEEL
centimators-0.3.2.dist-info/licenses/LICENSE
centimators-0.3.2.dist-info/RECORD
