Metadata-Version: 2.4
Name: centimators
Version: 0.3.2
Summary: essential data transformers and model estimators for ML and data science competitions
Author-email: jrosenfeld13 <jason@crowdcent.com>
License-File: LICENSE
Requires-Python: >=3.11
Requires-Dist: narwhals>=1.39.0
Requires-Dist: scikit-learn>=1.6.1
Provides-Extra: all
Requires-Dist: dspy>=2.6.24; extra == 'all'
Requires-Dist: jax>=0.6.31; extra == 'all'
Requires-Dist: jaxlib>=0.4.31; extra == 'all'
Requires-Dist: keras>=3.9.2; extra == 'all'
Requires-Dist: tqdm>=4.66.0; extra == 'all'
Requires-Dist: umap-learn>=0.5.9.post2; extra == 'all'
Provides-Extra: dspy
Requires-Dist: dspy>=2.6.24; extra == 'dspy'
Provides-Extra: keras-jax
Requires-Dist: jax>=0.6.31; extra == 'keras-jax'
Requires-Dist: jaxlib>=0.4.31; extra == 'keras-jax'
Requires-Dist: keras>=3.9.2; extra == 'keras-jax'
